my_module.cpython-310-x86_64-linux-gnu.so
aja_pose/__init__.py
aja_pose/data/annot/README.md
aja_pose/data/annot/ak_P1/test.json
aja_pose/data/annot/ak_P1/train.json
aja_pose/data/annot/ak_P2/test.json
aja_pose/data/annot/ak_P2/train.json
aja_pose/data/annot/ak_P3_amphibian/test.json
aja_pose/data/annot/ak_P3_amphibian/train.json
aja_pose/data/annot/ak_P3_bird/test.json
aja_pose/data/annot/ak_P3_bird/train.json
aja_pose/data/annot/ak_P3_fish/test.json
aja_pose/data/annot/ak_P3_fish/train.json
aja_pose/data/annot/ak_P3_mammal/test.json
aja_pose/data/annot/ak_P3_mammal/train.json
aja_pose/data/annot/ak_P3_reptile/test.json
aja_pose/data/annot/ak_P3_reptile/train.json
aja_pose/data/images/README.md
aja_pose/dataDir/0x0-horses-the-wings-of-mankind-1527015927739.jpg
aja_pose/dataDir/8q90217t58_Humpback_Whale_and_Calf_WW2131047.jpg
aja_pose/dataDir/ABJYRLSQ_f000034.jpg
aja_pose/dataDir/AdobeStock_96520936_541522_reduced.jpg
aja_pose/dataDir/Crocodile-Pic.jpg
aja_pose/dataDir/Dog Walk Cycle Animation Reference - 24fps.mp4
aja_pose/dataDir/Eastern-Brown-Snake-1200x800.jpg
aja_pose/dataDir/Full_Shot_of_a_Caribbean_Reef_Shark_at_Tiger_Beach_Bahamas.jpg
aja_pose/dataDir/SaltwaterCrocodile('Maximo').jpg
aja_pose/dataDir/Whale-Jumping.jpg
aja_pose/dataDir/animals_hero_lizards.jpg
aja_pose/dataDir/bird.jfif
aja_pose/dataDir/covergushter.jpg
aja_pose/dataDir/download (1).jfif
aja_pose/dataDir/download (2).jfif
aja_pose/dataDir/download (3).jfif
aja_pose/dataDir/download (4).jfif
aja_pose/dataDir/download (5).jfif
aja_pose/dataDir/download (6).jfif
aja_pose/dataDir/download.jfif
aja_pose/dataDir/high-angle-view-of-humpback-whale-swimming-in-sea-royalty-free-image-1702574312.jpg
aja_pose/dataDir/images (1).jfif
aja_pose/dataDir/images (2).jfif
aja_pose/dataDir/images (3).jfif
aja_pose/dataDir/images.jfif
aja_pose/dataDir/licensed-image.jfif
aja_pose/dataDir/moderncrocodile_rutpratheep_nilpechr_500.jpeg
aja_pose/dataDir/pexels-helena-lopes-1996333.jpg
aja_pose-0.0.1.dist-info/METADATA
aja_pose-0.0.1.dist-info/WHEEL
aja_pose-0.0.1.dist-info/top_level.txt
aja_pose-0.0.1.dist-info/RECORD
