Metadata-Version: 2.1
Name: aja-pose
Version: 0.0.1
Summary: Animal pose estimation using Vision Transformers and HRNet(VHR)
Home-page: https://github.com/Antony-gitau/2024_ICME_Challenge
Author: Austin Kaburia, Joan Kabura, Antony Gitau
Author-email: kaburiaaustin1@gmail.com, joankabura1@gmail.com, antonym.gitau9@gmail.com
Requires-Python: >=3.8
Requires-Dist: absl-py
Requires-Dist: beautifulsoup4 ==4.12.3
Requires-Dist: cachetools ==5.3.3
Requires-Dist: certifi ==2024.2.2
Requires-Dist: charset-normalizer ==3.3.2
Requires-Dist: contourpy ==1.1.1
Requires-Dist: cycler ==0.12.1
Requires-Dist: Cython ==3.0.9
Requires-Dist: dataclasses ==0.6
Requires-Dist: easydict ==1.13
Requires-Dist: einops ==0.7.0
Requires-Dist: filelock ==3.13.1
Requires-Dist: fonttools ==4.49.0
Requires-Dist: fsspec
Requires-Dist: future ==1.0.0
Requires-Dist: grpcio ==1.62.0
Requires-Dist: idna ==3.6
Requires-Dist: imageio ==2.34.0
Requires-Dist: importlib-metadata ==7.0.2
Requires-Dist: importlib-resources ==6.1.3
Requires-Dist: Jinja2 ==3.1.3
Requires-Dist: json-tricks ==3.17.3
Requires-Dist: kiwisolver ==1.4.5
Requires-Dist: lazy-loader ==0.3
Requires-Dist: Markdown ==3.5.2
Requires-Dist: MarkupSafe ==2.1.5
Requires-Dist: matplotlib ==3.7.5
Requires-Dist: mpmath ==1.3.0
Requires-Dist: networkx ==3.1
Requires-Dist: numpy
Requires-Dist: oauthlib ==3.2.2
Requires-Dist: opencv-python ==4.9.0.80
Requires-Dist: packaging ==23.2
Requires-Dist: pandas
Requires-Dist: pillow ==10.2.0
Requires-Dist: protobuf ==3.20.3
Requires-Dist: pyasn1 ==0.5.1
Requires-Dist: pyasn1-modules ==0.3.0
Requires-Dist: pycocotools ==2.0.7
Requires-Dist: pyparsing ==3.1.2
Requires-Dist: PySocks ==1.7.1
Requires-Dist: python-dateutil ==2.9.0.post0
Requires-Dist: pytz ==2024.1
Requires-Dist: PyWavelets ==1.4.1
Requires-Dist: PyYAML ==6.0.1
Requires-Dist: requests ==2.31.0
Requires-Dist: requests-oauthlib ==1.3.1
Requires-Dist: rsa ==4.9
Requires-Dist: scikit-image ==0.21.0
Requires-Dist: scipy ==1.10.1
Requires-Dist: shapely ==2.0.3
Requires-Dist: six ==1.16.0
Requires-Dist: soupsieve ==2.5
Requires-Dist: sympy ==1.12
Requires-Dist: tensorboard ==2.15.0
Requires-Dist: tensorboard-data-server ==0.7.2
Requires-Dist: tensorboardX ==2.6.2.2
Requires-Dist: tifffile ==2023.7.10
Requires-Dist: timm
Requires-Dist: torch ==2.2.1+cu121
Requires-Dist: torchvision ==0.17.1+cu121
Requires-Dist: torchaudio ==2.2.1+cu121
Requires-Dist: tqdm ==4.66.2
Requires-Dist: typing-extensions ==4.10.0
Requires-Dist: tzdata ==2024.1
Requires-Dist: urllib3 ==2.2.1
Requires-Dist: werkzeug ==3.0.1
Requires-Dist: yacs ==0.1.8
Requires-Dist: zipp ==3.17.0
